python_seatsurfing-0.4.1.dist-info/licenses/LICENSE
seatsurfing/__init__.py
seatsurfing/authentication.py
seatsurfing/booking.py
seatsurfing/space.py
seatsurfing/common/__init__.py
seatsurfing/common/http_client.py
seatsurfing/models/__init__.py
seatsurfing/models/authentication.py
seatsurfing/models/booking.py
python_seatsurfing-0.4.1.dist-info/METADATA
python_seatsurfing-0.4.1.dist-info/WHEEL
python_seatsurfing-0.4.1.dist-info/top_level.txt
python_seatsurfing-0.4.1.dist-info/RECORD
