Metadata-Version: 2.4
Name: python-seatsurfing
Version: 0.4.1
Summary: Python client to interface with Seatsurfing
Author: Zoltán Fraknói
Project-URL: Homepage, https://github.com/Vogete/python-seatsurfing
Classifier: Programming Language :: Python :: 3
Classifier: Operating System :: OS Independent
Requires-Python: >=3.9
License-File: LICENSE
Requires-Dist: httpx
Requires-Dist: pydantic>2.0.0
Dynamic: license-file
